Metadata-Version: 2.1
Name: ForceSpectroscopyHelper
Version: 0.3.2
Summary: NC-AFM experiment data IO, DF/F convert, 3D visualization tool.
Home-page: UNKNOWN
Author: ZHUO DIAO
Author-email: enzian0515@gmail.com
License: MIT
Platform: UNKNOWN
